djangosmsaero-1.0.0.dev1.dist-info/DESCRIPTION.rst
djangosmsaero-1.0.0.dev1.dist-info/METADATA
djangosmsaero-1.0.0.dev1.dist-info/RECORD
djangosmsaero-1.0.0.dev1.dist-info/WHEEL
djangosmsaero-1.0.0.dev1.dist-info/metadata.json
djangosmsaero-1.0.0.dev1.dist-info/top_level.txt
smsaero/__init__.py
smsaero/admin.py
smsaero/conf.py
smsaero/factories.py
smsaero/models.py
smsaero/tests.py
smsaero/urls.py
smsaero/utils.py
