Metadata-Version: 2.0
Name: djangosmsaero
Version: 1.0.0.dev1
Summary: A simple Django app for send SMS via smsaero.ru.
Home-page: http://github.com/nkonin/django_smsaero
Author: nkonin
Author-email: awesome@nkonin.me
License: MIT
Platform: UNKNOWN
Classifier: Environment :: Web Environment
Classifier: Framework :: Django
Classifier: Framework :: Django :: 1.10
Classifier: Intended Audience :: Developers
Classifier: License :: OSI Approved :: GNU Affero General Public License v3 or later (AGPLv3+)
Classifier: Operating System :: OS Independent
Classifier: Programming Language :: Python
Classifier: Programming Language :: Python :: 3.5
Classifier: Topic :: Internet :: WWW/HTTP
Classifier: Topic :: Internet :: WWW/HTTP :: Dynamic Content
Requires-Dist: django-rq
Requires-Dist: factory-boy
Requires-Dist: requests
